{
    "meta": {
        "id": 0,
        "date": "1714122630"
    },
    "entries": {
        "communityCreators": [
            {
                "id": "56tbCnsGMqXwri2eoLoRjK",
                "postDate": "1713597574",
                "expiryDate": null,
                "lang": "en",
                "section": "communityCreators",
                "type": "communityCreator",
                "author": "GuestContent",
                "name": "MyHayDay",
                "thumbnail": {
                    "small": {
                        "title": "Guest content creator 90 29a189a7 d876 4c98 bc4e 5619b04e3c3d xz6h",
                        "path": "/0rebc2l8z0wu/VceQXn8VpTYRecfd8PKHn_AR1W_-rr8J_HNKxQbFBqE/54450c983d8983c4473990ac9c9b2a92/1539741710_1665677633.jpeg?w=10&h=10&f=center&fit=fill",
                        "width": 10,
                        "height": 10
                    },
                    "smallRetina": {
                        "title": "Guest content creator 90 29a189a7 d876 4c98 bc4e 5619b04e3c3d xz6h",
                        "path": "/0rebc2l8z0wu/VceQXn8VpTYRecfd8PKHn_AR1W_-rr8J_HNKxQbFBqE/54450c983d8983c4473990ac9c9b2a92/1539741710_1665677633.jpeg?w=20&h=20&f=center&fit=fill",
                        "width": 20,
                        "height": 20
                    },
                    "medium": {
                        "title": "Guest content creator 90 29a189a7 d876 4c98 bc4e 5619b04e3c3d xz6h",
                        "path": "/0rebc2l8z0wu/VceQXn8VpTYRecfd8PKHn_AR1W_-rr8J_HNKxQbFBqE/54450c983d8983c4473990ac9c9b2a92/1539741710_1665677633.jpeg?w=25&h=25&f=center&fit=fill",
                        "width": 25,
                        "height": 25
                    },
                    "mediumRetina": {
                        "title": "Guest content creator 90 29a189a7 d876 4c98 bc4e 5619b04e3c3d xz6h",
                        "path": "/0rebc2l8z0wu/VceQXn8VpTYRecfd8PKHn_AR1W_-rr8J_HNKxQbFBqE/54450c983d8983c4473990ac9c9b2a92/1539741710_1665677633.jpeg?w=30&h=30&f=center&fit=fill",
                        "width": 30,
                        "height": 30
                    },
                    "large": {
                        "title": "Guest content creator 90 29a189a7 d876 4c98 bc4e 5619b04e3c3d xz6h",
                        "path": "/0rebc2l8z0wu/VceQXn8VpTYRecfd8PKHn_AR1W_-rr8J_HNKxQbFBqE/54450c983d8983c4473990ac9c9b2a92/1539741710_1665677633.jpeg?w=40&h=40&f=center&fit=fill",
                        "width": 40,
                        "height": 40
                    },
                    "largeRetina": {
                        "title": "Guest content creator 90 29a189a7 d876 4c98 bc4e 5619b04e3c3d xz6h",
                        "path": "/0rebc2l8z0wu/VceQXn8VpTYRecfd8PKHn_AR1W_-rr8J_HNKxQbFBqE/54450c983d8983c4473990ac9c9b2a92/1539741710_1665677633.jpeg?w=50&h=50&f=center&fit=fill",
                        "width": 50,
                        "height": 50
                    }
                },
                "creatorId": "90-29a189a7-d876-4c98-bc4e-5619b04e3c3d",
                "submissionInfo": "Submission Type: Portal\nUser ID: 90-29a189a7-d876-4c98-bc4e-5619b04e3c3d\nUser Name: MyHayDay"
            },
            {
                "id": "6zMydNOlsdinfcMLO3PLYX",
                "postDate": "1713597574",
                "expiryDate": null,
                "lang": "en",
                "section": "communityCreators",
                "type": "communityCreator",
                "author": "GuestContent",
                "name": "MyHayDay",
                "thumbnail": {
                    "small": {
                        "title": "Guest content creator 90 29a189a7 d876 4c98 bc4e 5619b04e3c3d xz6h",
                        "path": "/0rebc2l8z0wu/VceQXn8VpTYRecfd8PKHn_AR1W_-rr8J_HNKxQbFBqE/54450c983d8983c4473990ac9c9b2a92/1539741710_1665677633.jpeg?w=10&h=10&f=center&fit=fill",
                        "width": 10,
                        "height": 10
                    },
                    "smallRetina": {
                        "title": "Guest content creator 90 29a189a7 d876 4c98 bc4e 5619b04e3c3d xz6h",
                        "path": "/0rebc2l8z0wu/VceQXn8VpTYRecfd8PKHn_AR1W_-rr8J_HNKxQbFBqE/54450c983d8983c4473990ac9c9b2a92/1539741710_1665677633.jpeg?w=20&h=20&f=center&fit=fill",
                        "width": 20,
                        "height": 20
                    },
                    "medium": {
                        "title": "Guest content creator 90 29a189a7 d876 4c98 bc4e 5619b04e3c3d xz6h",
                        "path": "/0rebc2l8z0wu/VceQXn8VpTYRecfd8PKHn_AR1W_-rr8J_HNKxQbFBqE/54450c983d8983c4473990ac9c9b2a92/1539741710_1665677633.jpeg?w=25&h=25&f=center&fit=fill",
                        "width": 25,
                        "height": 25
                    },
                    "mediumRetina": {
                        "title": "Guest content creator 90 29a189a7 d876 4c98 bc4e 5619b04e3c3d xz6h",
                        "path": "/0rebc2l8z0wu/VceQXn8VpTYRecfd8PKHn_AR1W_-rr8J_HNKxQbFBqE/54450c983d8983c4473990ac9c9b2a92/1539741710_1665677633.jpeg?w=30&h=30&f=center&fit=fill",
                        "width": 30,
                        "height": 30
                    },
                    "large": {
                        "title": "Guest content creator 90 29a189a7 d876 4c98 bc4e 5619b04e3c3d xz6h",
                        "path": "/0rebc2l8z0wu/VceQXn8VpTYRecfd8PKHn_AR1W_-rr8J_HNKxQbFBqE/54450c983d8983c4473990ac9c9b2a92/1539741710_1665677633.jpeg?w=40&h=40&f=center&fit=fill",
                        "width": 40,
                        "height": 40
                    },
                    "largeRetina": {
                        "title": "Guest content creator 90 29a189a7 d876 4c98 bc4e 5619b04e3c3d xz6h",
                        "path": "/0rebc2l8z0wu/VceQXn8VpTYRecfd8PKHn_AR1W_-rr8J_HNKxQbFBqE/54450c983d8983c4473990ac9c9b2a92/1539741710_1665677633.jpeg?w=50&h=50&f=center&fit=fill",
                        "width": 50,
                        "height": 50
                    }
                },
                "creatorId": "90-29a189a7-d876-4c98-bc4e-5619b04e3c3d",
                "submissionInfo": "Submission Type: Portal\nUser ID: 90-29a189a7-d876-4c98-bc4e-5619b04e3c3d\nUser Name: MyHayDay"
            },
            {
                "id": "DLuYd9qKynb2hzttIqrPQ",
                "postDate": "1713109456",
                "expiryDate": null,
                "lang": "en",
                "section": "communityCreators",
                "type": "communityCreator",
                "author": "GuestContent",
                "name": "OJ",
                "thumbnail": {
                    "small": {
                        "title": "guest-content-creator-44-4835965c-19b3-41c9-a71d-53828f6cf934-mw6u.png",
                        "path": "/0rebc2l8z0wu/1PFUhImqip9bE7VnDcKtr2/289ab4b68f9a0f7dce04ed084bb29531/guest-content-creator-44-4835965c-19b3-41c9-a71d-53828f6cf934-mw6u.png-1713109450411?w=10&h=10&f=center&fit=fill",
                        "width": 10,
                        "height": 10
                    },
                    "smallRetina": {
                        "title": "guest-content-creator-44-4835965c-19b3-41c9-a71d-53828f6cf934-mw6u.png",
                        "path": "/0rebc2l8z0wu/1PFUhImqip9bE7VnDcKtr2/289ab4b68f9a0f7dce04ed084bb29531/guest-content-creator-44-4835965c-19b3-41c9-a71d-53828f6cf934-mw6u.png-1713109450411?w=20&h=20&f=center&fit=fill",
                        "width": 20,
                        "height": 20
                    },
                    "medium": {
                        "title": "guest-content-creator-44-4835965c-19b3-41c9-a71d-53828f6cf934-mw6u.png",
                        "path": "/0rebc2l8z0wu/1PFUhImqip9bE7VnDcKtr2/289ab4b68f9a0f7dce04ed084bb29531/guest-content-creator-44-4835965c-19b3-41c9-a71d-53828f6cf934-mw6u.png-1713109450411?w=25&h=25&f=center&fit=fill",
                        "width": 25,
                        "height": 25
                    },
                    "mediumRetina": {
                        "title": "guest-content-creator-44-4835965c-19b3-41c9-a71d-53828f6cf934-mw6u.png",
                        "path": "/0rebc2l8z0wu/1PFUhImqip9bE7VnDcKtr2/289ab4b68f9a0f7dce04ed084bb29531/guest-content-creator-44-4835965c-19b3-41c9-a71d-53828f6cf934-mw6u.png-1713109450411?w=30&h=30&f=center&fit=fill",
                        "width": 30,
                        "height": 30
                    },
                    "large": {
                        "title": "guest-content-creator-44-4835965c-19b3-41c9-a71d-53828f6cf934-mw6u.png",
                        "path": "/0rebc2l8z0wu/1PFUhImqip9bE7VnDcKtr2/289ab4b68f9a0f7dce04ed084bb29531/guest-content-creator-44-4835965c-19b3-41c9-a71d-53828f6cf934-mw6u.png-1713109450411?w=40&h=40&f=center&fit=fill",
                        "width": 40,
                        "height": 40
                    },
                    "largeRetina": {
                        "title": "guest-content-creator-44-4835965c-19b3-41c9-a71d-53828f6cf934-mw6u.png",
                        "path": "/0rebc2l8z0wu/1PFUhImqip9bE7VnDcKtr2/289ab4b68f9a0f7dce04ed084bb29531/guest-content-creator-44-4835965c-19b3-41c9-a71d-53828f6cf934-mw6u.png-1713109450411?w=50&h=50&f=center&fit=fill",
                        "width": 50,
                        "height": 50
                    }
                },
                "creatorId": "44-4835965c-19b3-41c9-a71d-53828f6cf934",
                "submissionInfo": "Submission Type: Portal\nUser ID: 44-4835965c-19b3-41c9-a71d-53828f6cf934\nUser Name: OJ"
            },
            {
                "id": "5vHt4fTDSyO57CHlkCtoon",
                "postDate": "1713084765",
                "expiryDate": null,
                "lang": "en",
                "section": "communityCreators",
                "type": "communityCreator",
                "author": "GuestContent",
                "name": "R3DKNIGHT",
                "thumbnail": {
                    "small": {
                        "title": "Guest content creator 88 1027c0c1 7b57 4c63 8a92 2c6ce47d910e eguh",
                        "path": "/0rebc2l8z0wu/L2j2r7ADuBaQmm1p9m5WCHMhLwDEU4Keap5aJYT9DGg/62f34cceeb563adf084fa29201e0d402/74821364_1656343701.png?w=10&h=10&f=center&fit=fill",
                        "width": 10,
                        "height": 10
                    },
                    "smallRetina": {
                        "title": "Guest content creator 88 1027c0c1 7b57 4c63 8a92 2c6ce47d910e eguh",
                        "path": "/0rebc2l8z0wu/L2j2r7ADuBaQmm1p9m5WCHMhLwDEU4Keap5aJYT9DGg/62f34cceeb563adf084fa29201e0d402/74821364_1656343701.png?w=20&h=20&f=center&fit=fill",
                        "width": 20,
                        "height": 20
                    },
                    "medium": {
                        "title": "Guest content creator 88 1027c0c1 7b57 4c63 8a92 2c6ce47d910e eguh",
                        "path": "/0rebc2l8z0wu/L2j2r7ADuBaQmm1p9m5WCHMhLwDEU4Keap5aJYT9DGg/62f34cceeb563adf084fa29201e0d402/74821364_1656343701.png?w=25&h=25&f=center&fit=fill",
                        "width": 25,
                        "height": 25
                    },
                    "mediumRetina": {
                        "title": "Guest content creator 88 1027c0c1 7b57 4c63 8a92 2c6ce47d910e eguh",
                        "path": "/0rebc2l8z0wu/L2j2r7ADuBaQmm1p9m5WCHMhLwDEU4Keap5aJYT9DGg/62f34cceeb563adf084fa29201e0d402/74821364_1656343701.png?w=30&h=30&f=center&fit=fill",
                        "width": 30,
                        "height": 30
                    },
                    "large": {
                        "title": "Guest content creator 88 1027c0c1 7b57 4c63 8a92 2c6ce47d910e eguh",
                        "path": "/0rebc2l8z0wu/L2j2r7ADuBaQmm1p9m5WCHMhLwDEU4Keap5aJYT9DGg/62f34cceeb563adf084fa29201e0d402/74821364_1656343701.png?w=40&h=40&f=center&fit=fill",
                        "width": 40,
                        "height": 40
                    },
                    "largeRetina": {
                        "title": "Guest content creator 88 1027c0c1 7b57 4c63 8a92 2c6ce47d910e eguh",
                        "path": "/0rebc2l8z0wu/L2j2r7ADuBaQmm1p9m5WCHMhLwDEU4Keap5aJYT9DGg/62f34cceeb563adf084fa29201e0d402/74821364_1656343701.png?w=50&h=50&f=center&fit=fill",
                        "width": 50,
                        "height": 50
                    }
                },
                "creatorId": "88-1027c0c1-7b57-4c63-8a92-2c6ce47d910e",
                "submissionInfo": "Submission Type: Portal\nUser ID: 88-1027c0c1-7b57-4c63-8a92-2c6ce47d910e\nUser Name: R3DKNIGHT"
            },
            {
                "id": "6bBnhMOycwUDg2ROj2jz88",
                "postDate": "1713597574",
                "expiryDate": null,
                "lang": "en",
                "section": "communityCreators",
                "type": "communityCreator",
                "author": "GuestContent",
                "name": "MyHayDay",
                "thumbnail": {
                    "small": {
                        "title": "Guest content creator 90 29a189a7 d876 4c98 bc4e 5619b04e3c3d xz6h",
                        "path": "/0rebc2l8z0wu/VceQXn8VpTYRecfd8PKHn_AR1W_-rr8J_HNKxQbFBqE/54450c983d8983c4473990ac9c9b2a92/1539741710_1665677633.jpeg?w=10&h=10&f=center&fit=fill",
                        "width": 10,
                        "height": 10
                    },
                    "smallRetina": {
                        "title": "Guest content creator 90 29a189a7 d876 4c98 bc4e 5619b04e3c3d xz6h",
                        "path": "/0rebc2l8z0wu/VceQXn8VpTYRecfd8PKHn_AR1W_-rr8J_HNKxQbFBqE/54450c983d8983c4473990ac9c9b2a92/1539741710_1665677633.jpeg?w=20&h=20&f=center&fit=fill",
                        "width": 20,
                        "height": 20
                    },
                    "medium": {
                        "title": "Guest content creator 90 29a189a7 d876 4c98 bc4e 5619b04e3c3d xz6h",
                        "path": "/0rebc2l8z0wu/VceQXn8VpTYRecfd8PKHn_AR1W_-rr8J_HNKxQbFBqE/54450c983d8983c4473990ac9c9b2a92/1539741710_1665677633.jpeg?w=25&h=25&f=center&fit=fill",
                        "width": 25,
                        "height": 25
                    },
                    "mediumRetina": {
                        "title": "Guest content creator 90 29a189a7 d876 4c98 bc4e 5619b04e3c3d xz6h",
                        "path": "/0rebc2l8z0wu/VceQXn8VpTYRecfd8PKHn_AR1W_-rr8J_HNKxQbFBqE/54450c983d8983c4473990ac9c9b2a92/1539741710_1665677633.jpeg?w=30&h=30&f=center&fit=fill",
                        "width": 30,
                        "height": 30
                    },
                    "large": {
                        "title": "Guest content creator 90 29a189a7 d876 4c98 bc4e 5619b04e3c3d xz6h",
                        "path": "/0rebc2l8z0wu/VceQXn8VpTYRecfd8PKHn_AR1W_-rr8J_HNKxQbFBqE/54450c983d8983c4473990ac9c9b2a92/1539741710_1665677633.jpeg?w=40&h=40&f=center&fit=fill",
                        "width": 40,
                        "height": 40
                    },
                    "largeRetina": {
                        "title": "Guest content creator 90 29a189a7 d876 4c98 bc4e 5619b04e3c3d xz6h",
                        "path": "/0rebc2l8z0wu/VceQXn8VpTYRecfd8PKHn_AR1W_-rr8J_HNKxQbFBqE/54450c983d8983c4473990ac9c9b2a92/1539741710_1665677633.jpeg?w=50&h=50&f=center&fit=fill",
                        "width": 50,
                        "height": 50
                    }
                },
                "creatorId": "90-29a189a7-d876-4c98-bc4e-5619b04e3c3d",
                "submissionInfo": "Submission Type: Portal\nUser ID: 90-29a189a7-d876-4c98-bc4e-5619b04e3c3d\nUser Name: MyHayDay"
            },
            {
                "id": "J38oKe0fpbmVjUwRrLHLK",
                "postDate": "1712509169",
                "expiryDate": null,
                "lang": "en",
                "section": "communityCreators",
                "type": "communityCreator",
                "author": "GuestContent",
                "name": "PILITUTORIALES",
                "thumbnail": {
                    "small": {
                        "title": "Guest content creator 62 5411181f 39a3 4f11 a9c9 acee127e5804 e33w",
                        "path": "/0rebc2l8z0wu/4hyDjXCuSc_VcpFtNaNsR7RqH2O66GTdoJ-6eGfvfkw/e1423111a5ce823c907b379dd885622d/1915246992_1688416005.jpeg?w=10&h=10&f=center&fit=fill",
                        "width": 10,
                        "height": 10
                    },
                    "smallRetina": {
                        "title": "Guest content creator 62 5411181f 39a3 4f11 a9c9 acee127e5804 e33w",
                        "path": "/0rebc2l8z0wu/4hyDjXCuSc_VcpFtNaNsR7RqH2O66GTdoJ-6eGfvfkw/e1423111a5ce823c907b379dd885622d/1915246992_1688416005.jpeg?w=20&h=20&f=center&fit=fill",
                        "width": 20,
                        "height": 20
                    },
                    "medium": {
                        "title": "Guest content creator 62 5411181f 39a3 4f11 a9c9 acee127e5804 e33w",
                        "path": "/0rebc2l8z0wu/4hyDjXCuSc_VcpFtNaNsR7RqH2O66GTdoJ-6eGfvfkw/e1423111a5ce823c907b379dd885622d/1915246992_1688416005.jpeg?w=25&h=25&f=center&fit=fill",
                        "width": 25,
                        "height": 25
                    },
                    "mediumRetina": {
                        "title": "Guest content creator 62 5411181f 39a3 4f11 a9c9 acee127e5804 e33w",
                        "path": "/0rebc2l8z0wu/4hyDjXCuSc_VcpFtNaNsR7RqH2O66GTdoJ-6eGfvfkw/e1423111a5ce823c907b379dd885622d/1915246992_1688416005.jpeg?w=30&h=30&f=center&fit=fill",
                        "width": 30,
                        "height": 30
                    },
                    "large": {
                        "title": "Guest content creator 62 5411181f 39a3 4f11 a9c9 acee127e5804 e33w",
                        "path": "/0rebc2l8z0wu/4hyDjXCuSc_VcpFtNaNsR7RqH2O66GTdoJ-6eGfvfkw/e1423111a5ce823c907b379dd885622d/1915246992_1688416005.jpeg?w=40&h=40&f=center&fit=fill",
                        "width": 40,
                        "height": 40
                    },
                    "largeRetina": {
                        "title": "Guest content creator 62 5411181f 39a3 4f11 a9c9 acee127e5804 e33w",
                        "path": "/0rebc2l8z0wu/4hyDjXCuSc_VcpFtNaNsR7RqH2O66GTdoJ-6eGfvfkw/e1423111a5ce823c907b379dd885622d/1915246992_1688416005.jpeg?w=50&h=50&f=center&fit=fill",
                        "width": 50,
                        "height": 50
                    }
                },
                "creatorId": "62-5411181f-39a3-4f11-a9c9-acee127e5804",
                "submissionInfo": "Submission Type: Portal\nUser ID: 62-5411181f-39a3-4f11-a9c9-acee127e5804\nUser Name: Hay Day PiliTutoriales"
            },
            {
                "id": "1xewzscdyGdpzQDrR41dh3",
                "postDate": "1713597574",
                "expiryDate": null,
                "lang": "en",
                "section": "communityCreators",
                "type": "communityCreator",
                "author": "GuestContent",
                "name": "MyHayDay",
                "thumbnail": {
                    "small": {
                        "title": "Guest content creator 90 29a189a7 d876 4c98 bc4e 5619b04e3c3d xz6h",
                        "path": "/0rebc2l8z0wu/VceQXn8VpTYRecfd8PKHn_AR1W_-rr8J_HNKxQbFBqE/54450c983d8983c4473990ac9c9b2a92/1539741710_1665677633.jpeg?w=10&h=10&f=center&fit=fill",
                        "width": 10,
                        "height": 10
                    },
                    "smallRetina": {
                        "title": "Guest content creator 90 29a189a7 d876 4c98 bc4e 5619b04e3c3d xz6h",
                        "path": "/0rebc2l8z0wu/VceQXn8VpTYRecfd8PKHn_AR1W_-rr8J_HNKxQbFBqE/54450c983d8983c4473990ac9c9b2a92/1539741710_1665677633.jpeg?w=20&h=20&f=center&fit=fill",
                        "width": 20,
                        "height": 20
                    },
                    "medium": {
                        "title": "Guest content creator 90 29a189a7 d876 4c98 bc4e 5619b04e3c3d xz6h",
                        "path": "/0rebc2l8z0wu/VceQXn8VpTYRecfd8PKHn_AR1W_-rr8J_HNKxQbFBqE/54450c983d8983c4473990ac9c9b2a92/1539741710_1665677633.jpeg?w=25&h=25&f=center&fit=fill",
                        "width": 25,
                        "height": 25
                    },
                    "mediumRetina": {
                        "title": "Guest content creator 90 29a189a7 d876 4c98 bc4e 5619b04e3c3d xz6h",
                        "path": "/0rebc2l8z0wu/VceQXn8VpTYRecfd8PKHn_AR1W_-rr8J_HNKxQbFBqE/54450c983d8983c4473990ac9c9b2a92/1539741710_1665677633.jpeg?w=30&h=30&f=center&fit=fill",
                        "width": 30,
                        "height": 30
                    },
                    "large": {
                        "title": "Guest content creator 90 29a189a7 d876 4c98 bc4e 5619b04e3c3d xz6h",
                        "path": "/0rebc2l8z0wu/VceQXn8VpTYRecfd8PKHn_AR1W_-rr8J_HNKxQbFBqE/54450c983d8983c4473990ac9c9b2a92/1539741710_1665677633.jpeg?w=40&h=40&f=center&fit=fill",
                        "width": 40,
                        "height": 40
                    },
                    "largeRetina": {
                        "title": "Guest content creator 90 29a189a7 d876 4c98 bc4e 5619b04e3c3d xz6h",
                        "path": "/0rebc2l8z0wu/VceQXn8VpTYRecfd8PKHn_AR1W_-rr8J_HNKxQbFBqE/54450c983d8983c4473990ac9c9b2a92/1539741710_1665677633.jpeg?w=50&h=50&f=center&fit=fill",
                        "width": 50,
                        "height": 50
                    }
                },
                "creatorId": "90-29a189a7-d876-4c98-bc4e-5619b04e3c3d",
                "submissionInfo": "Submission Type: Portal\nUser ID: 90-29a189a7-d876-4c98-bc4e-5619b04e3c3d\nUser Name: MyHayDay"
            },
            {
                "id": "6uXyD1PSdwmdsleiRmYjQT",
                "postDate": "1713597574",
                "expiryDate": null,
                "lang": "en",
                "section": "communityCreators",
                "type": "communityCreator",
                "author": "GuestContent",
                "name": "MyHayDay",
                "thumbnail": {
                    "small": {
                        "title": "Guest content creator 90 29a189a7 d876 4c98 bc4e 5619b04e3c3d xz6h",
                        "path": "/0rebc2l8z0wu/VceQXn8VpTYRecfd8PKHn_AR1W_-rr8J_HNKxQbFBqE/54450c983d8983c4473990ac9c9b2a92/1539741710_1665677633.jpeg?w=10&h=10&f=center&fit=fill",
                        "width": 10,
                        "height": 10
                    },
                    "smallRetina": {
                        "title": "Guest content creator 90 29a189a7 d876 4c98 bc4e 5619b04e3c3d xz6h",
                        "path": "/0rebc2l8z0wu/VceQXn8VpTYRecfd8PKHn_AR1W_-rr8J_HNKxQbFBqE/54450c983d8983c4473990ac9c9b2a92/1539741710_1665677633.jpeg?w=20&h=20&f=center&fit=fill",
                        "width": 20,
                        "height": 20
                    },
                    "medium": {
                        "title": "Guest content creator 90 29a189a7 d876 4c98 bc4e 5619b04e3c3d xz6h",
                        "path": "/0rebc2l8z0wu/VceQXn8VpTYRecfd8PKHn_AR1W_-rr8J_HNKxQbFBqE/54450c983d8983c4473990ac9c9b2a92/1539741710_1665677633.jpeg?w=25&h=25&f=center&fit=fill",
                        "width": 25,
                        "height": 25
                    },
                    "mediumRetina": {
                        "title": "Guest content creator 90 29a189a7 d876 4c98 bc4e 5619b04e3c3d xz6h",
                        "path": "/0rebc2l8z0wu/VceQXn8VpTYRecfd8PKHn_AR1W_-rr8J_HNKxQbFBqE/54450c983d8983c4473990ac9c9b2a92/1539741710_1665677633.jpeg?w=30&h=30&f=center&fit=fill",
                        "width": 30,
                        "height": 30
                    },
                    "large": {
                        "title": "Guest content creator 90 29a189a7 d876 4c98 bc4e 5619b04e3c3d xz6h",
                        "path": "/0rebc2l8z0wu/VceQXn8VpTYRecfd8PKHn_AR1W_-rr8J_HNKxQbFBqE/54450c983d8983c4473990ac9c9b2a92/1539741710_1665677633.jpeg?w=40&h=40&f=center&fit=fill",
                        "width": 40,
                        "height": 40
                    },
                    "largeRetina": {
                        "title": "Guest content creator 90 29a189a7 d876 4c98 bc4e 5619b04e3c3d xz6h",
                        "path": "/0rebc2l8z0wu/VceQXn8VpTYRecfd8PKHn_AR1W_-rr8J_HNKxQbFBqE/54450c983d8983c4473990ac9c9b2a92/1539741710_1665677633.jpeg?w=50&h=50&f=center&fit=fill",
                        "width": 50,
                        "height": 50
                    }
                },
                "creatorId": "90-29a189a7-d876-4c98-bc4e-5619b04e3c3d",
                "submissionInfo": "Submission Type: Portal\nUser ID: 90-29a189a7-d876-4c98-bc4e-5619b04e3c3d\nUser Name: MyHayDay"
            },
            {
                "id": "16DbCMlBWhLZbLz6wVWi1K",
                "postDate": "1713084765",
                "expiryDate": null,
                "lang": "en",
                "section": "communityCreators",
                "type": "communityCreator",
                "author": "GuestContent",
                "name": "R3DKNIGHT",
                "thumbnail": {
                    "small": {
                        "title": "Guest content creator 88 1027c0c1 7b57 4c63 8a92 2c6ce47d910e eguh",
                        "path": "/0rebc2l8z0wu/L2j2r7ADuBaQmm1p9m5WCHMhLwDEU4Keap5aJYT9DGg/62f34cceeb563adf084fa29201e0d402/74821364_1656343701.png?w=10&h=10&f=center&fit=fill",
                        "width": 10,
                        "height": 10
                    },
                    "smallRetina": {
                        "title": "Guest content creator 88 1027c0c1 7b57 4c63 8a92 2c6ce47d910e eguh",
                        "path": "/0rebc2l8z0wu/L2j2r7ADuBaQmm1p9m5WCHMhLwDEU4Keap5aJYT9DGg/62f34cceeb563adf084fa29201e0d402/74821364_1656343701.png?w=20&h=20&f=center&fit=fill",
                        "width": 20,
                        "height": 20
                    },
                    "medium": {
                        "title": "Guest content creator 88 1027c0c1 7b57 4c63 8a92 2c6ce47d910e eguh",
                        "path": "/0rebc2l8z0wu/L2j2r7ADuBaQmm1p9m5WCHMhLwDEU4Keap5aJYT9DGg/62f34cceeb563adf084fa29201e0d402/74821364_1656343701.png?w=25&h=25&f=center&fit=fill",
                        "width": 25,
                        "height": 25
                    },
                    "mediumRetina": {
                        "title": "Guest content creator 88 1027c0c1 7b57 4c63 8a92 2c6ce47d910e eguh",
                        "path": "/0rebc2l8z0wu/L2j2r7ADuBaQmm1p9m5WCHMhLwDEU4Keap5aJYT9DGg/62f34cceeb563adf084fa29201e0d402/74821364_1656343701.png?w=30&h=30&f=center&fit=fill",
                        "width": 30,
                        "height": 30
                    },
                    "large": {
                        "title": "Guest content creator 88 1027c0c1 7b57 4c63 8a92 2c6ce47d910e eguh",
                        "path": "/0rebc2l8z0wu/L2j2r7ADuBaQmm1p9m5WCHMhLwDEU4Keap5aJYT9DGg/62f34cceeb563adf084fa29201e0d402/74821364_1656343701.png?w=40&h=40&f=center&fit=fill",
                        "width": 40,
                        "height": 40
                    },
                    "largeRetina": {
                        "title": "Guest content creator 88 1027c0c1 7b57 4c63 8a92 2c6ce47d910e eguh",
                        "path": "/0rebc2l8z0wu/L2j2r7ADuBaQmm1p9m5WCHMhLwDEU4Keap5aJYT9DGg/62f34cceeb563adf084fa29201e0d402/74821364_1656343701.png?w=50&h=50&f=center&fit=fill",
                        "width": 50,
                        "height": 50
                    }
                },
                "creatorId": "88-1027c0c1-7b57-4c63-8a92-2c6ce47d910e",
                "submissionInfo": "Submission Type: Portal\nUser ID: 88-1027c0c1-7b57-4c63-8a92-2c6ce47d910e\nUser Name: R3DKNIGHT"
            }
        ],
        "communityEntries": [
            {
                "id": "56tbCnsGMqXwri2eoLoRjK",
                "postDate": "1713597575",
                "expiryDate": null,
                "lang": "en",
                "section": "communityEntries",
                "categories": [],
                "title": "First Day Of Happy Earth Day Events 2024",
                "videoUrl": "https://youtu.be/J8CMfQOOCzg",
                "author": "GuestContent",
                "embedVideo": false,
                "thumbnail": {
                    "small": {
                        "title": "guest-content-video-90-29a189a7-d876-4c98-bc4e-5619b04e3c3d-pezk.jpeg",
                        "path": "/0rebc2l8z0wu/7LVPCkcEq4cP7feMjCAYj6/f791da8698d250c49bdca3a3d6eb5284/guest-content-video-90-29a189a7-d876-4c98-bc4e-5619b04e3c3d-pezk.jpeg-1713597569117?w=172&h=96&f=center&fit=fill",
                        "width": 172,
                        "height": 96
                    },
                    "smallRetina": {
                        "title": "guest-content-video-90-29a189a7-d876-4c98-bc4e-5619b04e3c3d-pezk.jpeg",
                        "path": "/0rebc2l8z0wu/7LVPCkcEq4cP7feMjCAYj6/f791da8698d250c49bdca3a3d6eb5284/guest-content-video-90-29a189a7-d876-4c98-bc4e-5619b04e3c3d-pezk.jpeg-1713597569117?w=344&h=193&f=center&fit=fill",
                        "width": 344,
                        "height": 193
                    },
                    "medium": {
                        "title": "guest-content-video-90-29a189a7-d876-4c98-bc4e-5619b04e3c3d-pezk.jpeg",
                        "path": "/0rebc2l8z0wu/7LVPCkcEq4cP7feMjCAYj6/f791da8698d250c49bdca3a3d6eb5284/guest-content-video-90-29a189a7-d876-4c98-bc4e-5619b04e3c3d-pezk.jpeg-1713597569117?w=430&h=241&f=center&fit=fill",
                        "width": 430,
                        "height": 241
                    },
                    "mediumRetina": {
                        "title": "guest-content-video-90-29a189a7-d876-4c98-bc4e-5619b04e3c3d-pezk.jpeg",
                        "path": "/0rebc2l8z0wu/7LVPCkcEq4cP7feMjCAYj6/f791da8698d250c49bdca3a3d6eb5284/guest-content-video-90-29a189a7-d876-4c98-bc4e-5619b04e3c3d-pezk.jpeg-1713597569117?w=516&h=289&f=center&fit=fill",
                        "width": 516,
                        "height": 289
                    },
                    "large": {
                        "title": "guest-content-video-90-29a189a7-d876-4c98-bc4e-5619b04e3c3d-pezk.jpeg",
                        "path": "/0rebc2l8z0wu/7LVPCkcEq4cP7feMjCAYj6/f791da8698d250c49bdca3a3d6eb5284/guest-content-video-90-29a189a7-d876-4c98-bc4e-5619b04e3c3d-pezk.jpeg-1713597569117?w=688&h=386&f=center&fit=fill",
                        "width": 688,
                        "height": 386
                    },
                    "largeRetina": {
                        "title": "guest-content-video-90-29a189a7-d876-4c98-bc4e-5619b04e3c3d-pezk.jpeg",
                        "path": "/0rebc2l8z0wu/7LVPCkcEq4cP7feMjCAYj6/f791da8698d250c49bdca3a3d6eb5284/guest-content-video-90-29a189a7-d876-4c98-bc4e-5619b04e3c3d-pezk.jpeg-1713597569117?w=860&h=482&f=center&fit=fill",
                        "width": 860,
                        "height": 482
                    }
                },
                "submissionInfo": "Submission Type: Portal\nUser ID: 90-29a189a7-d876-4c98-bc4e-5619b04e3c3d\nUser Name: MyHayDay",
                "creator": {
                    "7iq6CF8ZXrdL4yb-ucm5s9Ap-No6mCSJGLCVZxaWQNI": {
                        "type": "communityCreator",
                        "name": "MyHayDay",
                        "creatorId": "90-29a189a7-d876-4c98-bc4e-5619b04e3c3d",
                        "submissionInfo": "Submission Type: Portal\nUser ID: 90-29a189a7-d876-4c98-bc4e-5619b04e3c3d\nUser Name: MyHayDay",
                        "thumbnail": {
                            "default": {
                                "height": 640,
                                "width": 640,
                                "title": "Guest content creator 90 29a189a7 d876 4c98 bc4e 5619b04e3c3d xz6h",
                                "path": "/0rebc2l8z0wu/VceQXn8VpTYRecfd8PKHn_AR1W_-rr8J_HNKxQbFBqE/54450c983d8983c4473990ac9c9b2a92/1539741710_1665677633.jpeg"
                            }
                        }
                    }
                },
                "embed": {
                    "url": "https://youtu.be/J8CMfQOOCzg",
                    "provider": "youtube",
                    "id": ""
                },
                "type": "communityEntry",
                "newUntil": "1713770366"
            },
            {
                "id": "6zMydNOlsdinfcMLO3PLYX",
                "postDate": "1713204439",
                "expiryDate": null,
                "lang": "en",
                "section": "communityEntries",
                "categories": [],
                "title": "Finish Farm Pass Season 41 in 15 Days",
                "videoUrl": "https://youtu.be/sjdhwOQ_Tag",
                "author": "GuestContent",
                "embedVideo": false,
                "thumbnail": {
                    "small": {
                        "title": "guest-content-video-90-29a189a7-d876-4c98-bc4e-5619b04e3c3d-ptou.jpeg",
                        "path": "/0rebc2l8z0wu/3QPlT5HJDSNwyaQXPtVHFA/07f478b53d0ee13f67515da61600e4a9/guest-content-video-90-29a189a7-d876-4c98-bc4e-5619b04e3c3d-ptou.jpeg-1713204432640?w=172&h=96&f=center&fit=fill",
                        "width": 172,
                        "height": 96
                    },
                    "smallRetina": {
                        "title": "guest-content-video-90-29a189a7-d876-4c98-bc4e-5619b04e3c3d-ptou.jpeg",
                        "path": "/0rebc2l8z0wu/3QPlT5HJDSNwyaQXPtVHFA/07f478b53d0ee13f67515da61600e4a9/guest-content-video-90-29a189a7-d876-4c98-bc4e-5619b04e3c3d-ptou.jpeg-1713204432640?w=344&h=193&f=center&fit=fill",
                        "width": 344,
                        "height": 193
                    },
                    "medium": {
                        "title": "guest-content-video-90-29a189a7-d876-4c98-bc4e-5619b04e3c3d-ptou.jpeg",
                        "path": "/0rebc2l8z0wu/3QPlT5HJDSNwyaQXPtVHFA/07f478b53d0ee13f67515da61600e4a9/guest-content-video-90-29a189a7-d876-4c98-bc4e-5619b04e3c3d-ptou.jpeg-1713204432640?w=430&h=241&f=center&fit=fill",
                        "width": 430,
                        "height": 241
                    },
                    "mediumRetina": {
                        "title": "guest-content-video-90-29a189a7-d876-4c98-bc4e-5619b04e3c3d-ptou.jpeg",
                        "path": "/0rebc2l8z0wu/3QPlT5HJDSNwyaQXPtVHFA/07f478b53d0ee13f67515da61600e4a9/guest-content-video-90-29a189a7-d876-4c98-bc4e-5619b04e3c3d-ptou.jpeg-1713204432640?w=516&h=289&f=center&fit=fill",
                        "width": 516,
                        "height": 289
                    },
                    "large": {
                        "title": "guest-content-video-90-29a189a7-d876-4c98-bc4e-5619b04e3c3d-ptou.jpeg",
                        "path": "/0rebc2l8z0wu/3QPlT5HJDSNwyaQXPtVHFA/07f478b53d0ee13f67515da61600e4a9/guest-content-video-90-29a189a7-d876-4c98-bc4e-5619b04e3c3d-ptou.jpeg-1713204432640?w=688&h=386&f=center&fit=fill",
                        "width": 688,
                        "height": 386
                    },
                    "largeRetina": {
                        "title": "guest-content-video-90-29a189a7-d876-4c98-bc4e-5619b04e3c3d-ptou.jpeg",
                        "path": "/0rebc2l8z0wu/3QPlT5HJDSNwyaQXPtVHFA/07f478b53d0ee13f67515da61600e4a9/guest-content-video-90-29a189a7-d876-4c98-bc4e-5619b04e3c3d-ptou.jpeg-1713204432640?w=860&h=482&f=center&fit=fill",
                        "width": 860,
                        "height": 482
                    }
                },
                "submissionInfo": "Submission Type: Portal\nUser ID: 90-29a189a7-d876-4c98-bc4e-5619b04e3c3d\nUser Name: MyHayDay",
                "creator": {
                    "7iq6CF8ZXrdL4yb-ucm5s9Ap-No6mCSJGLCVZxaWQNI": {
                        "type": "communityCreator",
                        "name": "MyHayDay",
                        "creatorId": "90-29a189a7-d876-4c98-bc4e-5619b04e3c3d",
                        "submissionInfo": "Submission Type: Portal\nUser ID: 90-29a189a7-d876-4c98-bc4e-5619b04e3c3d\nUser Name: MyHayDay",
                        "thumbnail": {
                            "default": {
                                "height": 640,
                                "width": 640,
                                "title": "Guest content creator 90 29a189a7 d876 4c98 bc4e 5619b04e3c3d xz6h",
                                "path": "/0rebc2l8z0wu/VceQXn8VpTYRecfd8PKHn_AR1W_-rr8J_HNKxQbFBqE/54450c983d8983c4473990ac9c9b2a92/1539741710_1665677633.jpeg"
                            }
                        }
                    }
                },
                "embed": {
                    "url": "https://youtu.be/sjdhwOQ_Tag",
                    "provider": "youtube",
                    "id": ""
                },
                "type": "communityEntry",
                "newUntil": "1713377230"
            },
            {
                "id": "DLuYd9qKynb2hzttIqrPQ",
                "postDate": "1713109457",
                "expiryDate": null,
                "lang": "en",
                "section": "communityEntries",
                "categories": [],
                "title": "i spent diamonds on wheat :(",
                "videoUrl": "https://www.youtube.com/watch?v=g-YbbjrL6SA",
                "author": "GuestContent",
                "embedVideo": false,
                "thumbnail": {
                    "small": {
                        "title": "guest-content-video-44-4835965c-19b3-41c9-a71d-53828f6cf934-nug6.png",
                        "path": "/0rebc2l8z0wu/5lZs1ogdIO34drieGeoa4C/284d604997ef9674f3b7963557956e3b/guest-content-video-44-4835965c-19b3-41c9-a71d-53828f6cf934-nug6.png-1713109450409?w=172&h=96&f=center&fit=fill",
                        "width": 172,
                        "height": 96
                    },
                    "smallRetina": {
                        "title": "guest-content-video-44-4835965c-19b3-41c9-a71d-53828f6cf934-nug6.png",
                        "path": "/0rebc2l8z0wu/5lZs1ogdIO34drieGeoa4C/284d604997ef9674f3b7963557956e3b/guest-content-video-44-4835965c-19b3-41c9-a71d-53828f6cf934-nug6.png-1713109450409?w=344&h=193&f=center&fit=fill",
                        "width": 344,
                        "height": 193
                    },
                    "medium": {
                        "title": "guest-content-video-44-4835965c-19b3-41c9-a71d-53828f6cf934-nug6.png",
                        "path": "/0rebc2l8z0wu/5lZs1ogdIO34drieGeoa4C/284d604997ef9674f3b7963557956e3b/guest-content-video-44-4835965c-19b3-41c9-a71d-53828f6cf934-nug6.png-1713109450409?w=430&h=241&f=center&fit=fill",
                        "width": 430,
                        "height": 241
                    },
                    "mediumRetina": {
                        "title": "guest-content-video-44-4835965c-19b3-41c9-a71d-53828f6cf934-nug6.png",
                        "path": "/0rebc2l8z0wu/5lZs1ogdIO34drieGeoa4C/284d604997ef9674f3b7963557956e3b/guest-content-video-44-4835965c-19b3-41c9-a71d-53828f6cf934-nug6.png-1713109450409?w=516&h=289&f=center&fit=fill",
                        "width": 516,
                        "height": 289
                    },
                    "large": {
                        "title": "guest-content-video-44-4835965c-19b3-41c9-a71d-53828f6cf934-nug6.png",
                        "path": "/0rebc2l8z0wu/5lZs1ogdIO34drieGeoa4C/284d604997ef9674f3b7963557956e3b/guest-content-video-44-4835965c-19b3-41c9-a71d-53828f6cf934-nug6.png-1713109450409?w=688&h=386&f=center&fit=fill",
                        "width": 688,
                        "height": 386
                    },
                    "largeRetina": {
                        "title": "guest-content-video-44-4835965c-19b3-41c9-a71d-53828f6cf934-nug6.png",
                        "path": "/0rebc2l8z0wu/5lZs1ogdIO34drieGeoa4C/284d604997ef9674f3b7963557956e3b/guest-content-video-44-4835965c-19b3-41c9-a71d-53828f6cf934-nug6.png-1713109450409?w=860&h=482&f=center&fit=fill",
                        "width": 860,
                        "height": 482
                    }
                },
                "submissionInfo": "Submission Type: Portal\nUser ID: 44-4835965c-19b3-41c9-a71d-53828f6cf934\nUser Name: OJ",
                "creator": {
                    "5nMi5Jx90nxbPsuV0GJ2U4": {
                        "type": "communityCreator",
                        "name": "OJ",
                        "creatorId": "44-4835965c-19b3-41c9-a71d-53828f6cf934",
                        "submissionInfo": "Submission Type: Portal\nUser ID: 44-4835965c-19b3-41c9-a71d-53828f6cf934\nUser Name: OJ",
                        "thumbnail": {
                            "default": {
                                "height": 56,
                                "width": 56,
                                "title": "guest-content-creator-44-4835965c-19b3-41c9-a71d-53828f6cf934-mw6u.png",
                                "path": "/0rebc2l8z0wu/1PFUhImqip9bE7VnDcKtr2/289ab4b68f9a0f7dce04ed084bb29531/guest-content-creator-44-4835965c-19b3-41c9-a71d-53828f6cf934-mw6u.png-1713109450411"
                            }
                        }
                    }
                },
                "embed": {
                    "url": "https://www.youtube.com/watch?v=g-YbbjrL6SA",
                    "provider": "youtube",
                    "id": ""
                },
                "type": "communityEntry",
                "newUntil": "1713282249"
            },
            {
                "id": "5vHt4fTDSyO57CHlkCtoon",
                "postDate": "1713084766",
                "expiryDate": null,
                "lang": "en",
                "section": "communityEntries",
                "categories": [],
                "title": "How to Make an Avatar, Player ID",
                "videoUrl": "https://youtu.be/Lg4HEUQTptc",
                "author": "GuestContent",
                "embedVideo": false,
                "thumbnail": {
                    "small": {
                        "title": "guest-content-video-88-1027c0c1-7b57-4c63-8a92-2c6ce47d910e-pzxq.png",
                        "path": "/0rebc2l8z0wu/7J9jJKX7R5A4mtu2YWNNEK/51ecb33b77458e0b73788cb09160961c/guest-content-video-88-1027c0c1-7b57-4c63-8a92-2c6ce47d910e-pzxq.png-1713084759671?w=172&h=96&f=center&fit=fill",
                        "width": 172,
                        "height": 96
                    },
                    "smallRetina": {
                        "title": "guest-content-video-88-1027c0c1-7b57-4c63-8a92-2c6ce47d910e-pzxq.png",
                        "path": "/0rebc2l8z0wu/7J9jJKX7R5A4mtu2YWNNEK/51ecb33b77458e0b73788cb09160961c/guest-content-video-88-1027c0c1-7b57-4c63-8a92-2c6ce47d910e-pzxq.png-1713084759671?w=344&h=193&f=center&fit=fill",
                        "width": 344,
                        "height": 193
                    },
                    "medium": {
                        "title": "guest-content-video-88-1027c0c1-7b57-4c63-8a92-2c6ce47d910e-pzxq.png",
                        "path": "/0rebc2l8z0wu/7J9jJKX7R5A4mtu2YWNNEK/51ecb33b77458e0b73788cb09160961c/guest-content-video-88-1027c0c1-7b57-4c63-8a92-2c6ce47d910e-pzxq.png-1713084759671?w=430&h=241&f=center&fit=fill",
                        "width": 430,
                        "height": 241
                    },
                    "mediumRetina": {
                        "title": "guest-content-video-88-1027c0c1-7b57-4c63-8a92-2c6ce47d910e-pzxq.png",
                        "path": "/0rebc2l8z0wu/7J9jJKX7R5A4mtu2YWNNEK/51ecb33b77458e0b73788cb09160961c/guest-content-video-88-1027c0c1-7b57-4c63-8a92-2c6ce47d910e-pzxq.png-1713084759671?w=516&h=289&f=center&fit=fill",
                        "width": 516,
                        "height": 289
                    },
                    "large": {
                        "title": "guest-content-video-88-1027c0c1-7b57-4c63-8a92-2c6ce47d910e-pzxq.png",
                        "path": "/0rebc2l8z0wu/7J9jJKX7R5A4mtu2YWNNEK/51ecb33b77458e0b73788cb09160961c/guest-content-video-88-1027c0c1-7b57-4c63-8a92-2c6ce47d910e-pzxq.png-1713084759671?w=688&h=386&f=center&fit=fill",
                        "width": 688,
                        "height": 386
                    },
                    "largeRetina": {
                        "title": "guest-content-video-88-1027c0c1-7b57-4c63-8a92-2c6ce47d910e-pzxq.png",
                        "path": "/0rebc2l8z0wu/7J9jJKX7R5A4mtu2YWNNEK/51ecb33b77458e0b73788cb09160961c/guest-content-video-88-1027c0c1-7b57-4c63-8a92-2c6ce47d910e-pzxq.png-1713084759671?w=860&h=482&f=center&fit=fill",
                        "width": 860,
                        "height": 482
                    }
                },
                "submissionInfo": "Submission Type: Portal\nUser ID: 88-1027c0c1-7b57-4c63-8a92-2c6ce47d910e\nUser Name: R3DKNIGHT",
                "creator": {
                    "ZgedE6WKnqIRZTFt1zeNmsTRfHmliZyKTNPx1xfU2gg": {
                        "type": "communityCreator",
                        "name": "R3DKNIGHT",
                        "creatorId": "88-1027c0c1-7b57-4c63-8a92-2c6ce47d910e",
                        "submissionInfo": "Submission Type: Portal\nUser ID: 88-1027c0c1-7b57-4c63-8a92-2c6ce47d910e\nUser Name: R3DKNIGHT",
                        "thumbnail": {
                            "default": {
                                "height": 50,
                                "width": 50,
                                "title": "Guest content creator 88 1027c0c1 7b57 4c63 8a92 2c6ce47d910e eguh",
                                "path": "/0rebc2l8z0wu/L2j2r7ADuBaQmm1p9m5WCHMhLwDEU4Keap5aJYT9DGg/62f34cceeb563adf084fa29201e0d402/74821364_1656343701.png"
                            }
                        }
                    }
                },
                "embed": {
                    "url": "https://youtu.be/Lg4HEUQTptc",
                    "provider": "youtube",
                    "id": ""
                },
                "type": "communityEntry",
                "newUntil": "1713257559"
            },
            {
                "id": "6bBnhMOycwUDg2ROj2jz88",
                "postDate": "1711802952",
                "expiryDate": null,
                "lang": "en",
                "section": "communityEntries",
                "categories": [],
                "title": "Collecting Greg's Eggs Events 2024",
                "videoUrl": "https://youtu.be/l9dqBOErgyY",
                "author": "GuestContent",
                "embedVideo": false,
                "thumbnail": {
                    "small": {
                        "title": "guest-content-video-90-29a189a7-d876-4c98-bc4e-5619b04e3c3d-97pk.jpeg",
                        "path": "/0rebc2l8z0wu/63fwP4Rm9fs2T0d8qiLBan/b49b3b748418fa9e99b749021bb6e5cd/guest-content-video-90-29a189a7-d876-4c98-bc4e-5619b04e3c3d-97pk.jpeg-1711802946432?w=172&h=96&f=center&fit=fill",
                        "width": 172,
                        "height": 96
                    },
                    "smallRetina": {
                        "title": "guest-content-video-90-29a189a7-d876-4c98-bc4e-5619b04e3c3d-97pk.jpeg",
                        "path": "/0rebc2l8z0wu/63fwP4Rm9fs2T0d8qiLBan/b49b3b748418fa9e99b749021bb6e5cd/guest-content-video-90-29a189a7-d876-4c98-bc4e-5619b04e3c3d-97pk.jpeg-1711802946432?w=344&h=193&f=center&fit=fill",
                        "width": 344,
                        "height": 193
                    },
                    "medium": {
                        "title": "guest-content-video-90-29a189a7-d876-4c98-bc4e-5619b04e3c3d-97pk.jpeg",
                        "path": "/0rebc2l8z0wu/63fwP4Rm9fs2T0d8qiLBan/b49b3b748418fa9e99b749021bb6e5cd/guest-content-video-90-29a189a7-d876-4c98-bc4e-5619b04e3c3d-97pk.jpeg-1711802946432?w=430&h=241&f=center&fit=fill",
                        "width": 430,
                        "height": 241
                    },
                    "mediumRetina": {
                        "title": "guest-content-video-90-29a189a7-d876-4c98-bc4e-5619b04e3c3d-97pk.jpeg",
                        "path": "/0rebc2l8z0wu/63fwP4Rm9fs2T0d8qiLBan/b49b3b748418fa9e99b749021bb6e5cd/guest-content-video-90-29a189a7-d876-4c98-bc4e-5619b04e3c3d-97pk.jpeg-1711802946432?w=516&h=289&f=center&fit=fill",
                        "width": 516,
                        "height": 289
                    },
                    "large": {
                        "title": "guest-content-video-90-29a189a7-d876-4c98-bc4e-5619b04e3c3d-97pk.jpeg",
                        "path": "/0rebc2l8z0wu/63fwP4Rm9fs2T0d8qiLBan/b49b3b748418fa9e99b749021bb6e5cd/guest-content-video-90-29a189a7-d876-4c98-bc4e-5619b04e3c3d-97pk.jpeg-1711802946432?w=688&h=386&f=center&fit=fill",
                        "width": 688,
                        "height": 386
                    },
                    "largeRetina": {
                        "title": "guest-content-video-90-29a189a7-d876-4c98-bc4e-5619b04e3c3d-97pk.jpeg",
                        "path": "/0rebc2l8z0wu/63fwP4Rm9fs2T0d8qiLBan/b49b3b748418fa9e99b749021bb6e5cd/guest-content-video-90-29a189a7-d876-4c98-bc4e-5619b04e3c3d-97pk.jpeg-1711802946432?w=860&h=482&f=center&fit=fill",
                        "width": 860,
                        "height": 482
                    }
                },
                "submissionInfo": "Submission Type: Portal\nUser ID: 90-29a189a7-d876-4c98-bc4e-5619b04e3c3d\nUser Name: MyHayDay",
                "creator": {
                    "7iq6CF8ZXrdL4yb-ucm5s9Ap-No6mCSJGLCVZxaWQNI": {
                        "type": "communityCreator",
                        "name": "MyHayDay",
                        "creatorId": "90-29a189a7-d876-4c98-bc4e-5619b04e3c3d",
                        "submissionInfo": "Submission Type: Portal\nUser ID: 90-29a189a7-d876-4c98-bc4e-5619b04e3c3d\nUser Name: MyHayDay",
                        "thumbnail": {
                            "default": {
                                "height": 640,
                                "width": 640,
                                "title": "Guest content creator 90 29a189a7 d876 4c98 bc4e 5619b04e3c3d xz6h",
                                "path": "/0rebc2l8z0wu/VceQXn8VpTYRecfd8PKHn_AR1W_-rr8J_HNKxQbFBqE/54450c983d8983c4473990ac9c9b2a92/1539741710_1665677633.jpeg"
                            }
                        }
                    }
                },
                "embed": {
                    "url": "https://youtu.be/l9dqBOErgyY",
                    "provider": "youtube",
                    "id": ""
                },
                "type": "communityEntry",
                "newUntil": "1711975745"
            },
            {
                "id": "J38oKe0fpbmVjUwRrLHLK",
                "postDate": "1707671862",
                "expiryDate": null,
                "lang": "en",
                "section": "communityEntries",
                "categories": [],
                "title": "El Haka, la danza tradicional de Nueva Zelanda Valle T53",
                "videoUrl": "https://youtu.be/JMUf05kV7OQ",
                "author": "GuestContent",
                "embedVideo": false,
                "thumbnail": {
                    "small": {
                        "title": "guest-content-video-62-5411181f-39a3-4f11-a9c9-acee127e5804-oy3k.jpeg",
                        "path": "/0rebc2l8z0wu/6jryEYIV9dYc3rnGgXuiha/517d748c757c420b0d0bbe8567b33fe3/guest-content-video-62-5411181f-39a3-4f11-a9c9-acee127e5804-oy3k.jpeg-1707671855985?w=172&h=96&f=center&fit=fill",
                        "width": 172,
                        "height": 96
                    },
                    "smallRetina": {
                        "title": "guest-content-video-62-5411181f-39a3-4f11-a9c9-acee127e5804-oy3k.jpeg",
                        "path": "/0rebc2l8z0wu/6jryEYIV9dYc3rnGgXuiha/517d748c757c420b0d0bbe8567b33fe3/guest-content-video-62-5411181f-39a3-4f11-a9c9-acee127e5804-oy3k.jpeg-1707671855985?w=344&h=193&f=center&fit=fill",
                        "width": 344,
                        "height": 193
                    },
                    "medium": {
                        "title": "guest-content-video-62-5411181f-39a3-4f11-a9c9-acee127e5804-oy3k.jpeg",
                        "path": "/0rebc2l8z0wu/6jryEYIV9dYc3rnGgXuiha/517d748c757c420b0d0bbe8567b33fe3/guest-content-video-62-5411181f-39a3-4f11-a9c9-acee127e5804-oy3k.jpeg-1707671855985?w=430&h=241&f=center&fit=fill",
                        "width": 430,
                        "height": 241
                    },
                    "mediumRetina": {
                        "title": "guest-content-video-62-5411181f-39a3-4f11-a9c9-acee127e5804-oy3k.jpeg",
                        "path": "/0rebc2l8z0wu/6jryEYIV9dYc3rnGgXuiha/517d748c757c420b0d0bbe8567b33fe3/guest-content-video-62-5411181f-39a3-4f11-a9c9-acee127e5804-oy3k.jpeg-1707671855985?w=516&h=289&f=center&fit=fill",
                        "width": 516,
                        "height": 289
                    },
                    "large": {
                        "title": "guest-content-video-62-5411181f-39a3-4f11-a9c9-acee127e5804-oy3k.jpeg",
                        "path": "/0rebc2l8z0wu/6jryEYIV9dYc3rnGgXuiha/517d748c757c420b0d0bbe8567b33fe3/guest-content-video-62-5411181f-39a3-4f11-a9c9-acee127e5804-oy3k.jpeg-1707671855985?w=688&h=386&f=center&fit=fill",
                        "width": 688,
                        "height": 386
                    },
                    "largeRetina": {
                        "title": "guest-content-video-62-5411181f-39a3-4f11-a9c9-acee127e5804-oy3k.jpeg",
                        "path": "/0rebc2l8z0wu/6jryEYIV9dYc3rnGgXuiha/517d748c757c420b0d0bbe8567b33fe3/guest-content-video-62-5411181f-39a3-4f11-a9c9-acee127e5804-oy3k.jpeg-1707671855985?w=860&h=482&f=center&fit=fill",
                        "width": 860,
                        "height": 482
                    }
                },
                "submissionInfo": "Submission Type: Portal\nUser ID: 62-5411181f-39a3-4f11-a9c9-acee127e5804\nUser Name: Hay Day PiliTutoriales",
                "creator": {
                    "sUGV4jNmvmKSnoFE6QYmeoZxs6LgiM489BOCgD3NYU8": {
                        "type": "communityCreator",
                        "name": "PILITUTORIALES",
                        "creatorId": "62-5411181f-39a3-4f11-a9c9-acee127e5804",
                        "submissionInfo": "Submission Type: Portal\nUser ID: 62-5411181f-39a3-4f11-a9c9-acee127e5804\nUser Name: Hay Day PiliTutoriales",
                        "thumbnail": {
                            "default": {
                                "height": 386,
                                "width": 386,
                                "title": "Guest content creator 62 5411181f 39a3 4f11 a9c9 acee127e5804 e33w",
                                "path": "/0rebc2l8z0wu/4hyDjXCuSc_VcpFtNaNsR7RqH2O66GTdoJ-6eGfvfkw/e1423111a5ce823c907b379dd885622d/1915246992_1688416005.jpeg"
                            }
                        }
                    }
                },
                "embed": {
                    "url": "https://youtu.be/JMUf05kV7OQ",
                    "provider": "youtube",
                    "id": ""
                },
                "type": "communityEntry",
                "newUntil": "1707844655"
            },
            {
                "id": "1xewzscdyGdpzQDrR41dh3",
                "postDate": "1707389399",
                "expiryDate": null,
                "lang": "en",
                "section": "communityEntries",
                "categories": [],
                "title": "First Day Of Lovely Heart Task Event 2024",
                "videoUrl": "https://youtu.be/yDylV6Ww1Cw",
                "author": "GuestContent",
                "embedVideo": false,
                "thumbnail": {
                    "small": {
                        "title": "guest-content-video-90-29a189a7-d876-4c98-bc4e-5619b04e3c3d-bu5v.jpeg",
                        "path": "/0rebc2l8z0wu/6yBVlZPMTwQz9uu40asSIK/3a954d2f79d1b166fe087b8d47003640/guest-content-video-90-29a189a7-d876-4c98-bc4e-5619b04e3c3d-bu5v.jpeg-1707389392904?w=172&h=96&f=center&fit=fill",
                        "width": 172,
                        "height": 96
                    },
                    "smallRetina": {
                        "title": "guest-content-video-90-29a189a7-d876-4c98-bc4e-5619b04e3c3d-bu5v.jpeg",
                        "path": "/0rebc2l8z0wu/6yBVlZPMTwQz9uu40asSIK/3a954d2f79d1b166fe087b8d47003640/guest-content-video-90-29a189a7-d876-4c98-bc4e-5619b04e3c3d-bu5v.jpeg-1707389392904?w=344&h=193&f=center&fit=fill",
                        "width": 344,
                        "height": 193
                    },
                    "medium": {
                        "title": "guest-content-video-90-29a189a7-d876-4c98-bc4e-5619b04e3c3d-bu5v.jpeg",
                        "path": "/0rebc2l8z0wu/6yBVlZPMTwQz9uu40asSIK/3a954d2f79d1b166fe087b8d47003640/guest-content-video-90-29a189a7-d876-4c98-bc4e-5619b04e3c3d-bu5v.jpeg-1707389392904?w=430&h=241&f=center&fit=fill",
                        "width": 430,
                        "height": 241
                    },
                    "mediumRetina": {
                        "title": "guest-content-video-90-29a189a7-d876-4c98-bc4e-5619b04e3c3d-bu5v.jpeg",
                        "path": "/0rebc2l8z0wu/6yBVlZPMTwQz9uu40asSIK/3a954d2f79d1b166fe087b8d47003640/guest-content-video-90-29a189a7-d876-4c98-bc4e-5619b04e3c3d-bu5v.jpeg-1707389392904?w=516&h=289&f=center&fit=fill",
                        "width": 516,
                        "height": 289
                    },
                    "large": {
                        "title": "guest-content-video-90-29a189a7-d876-4c98-bc4e-5619b04e3c3d-bu5v.jpeg",
                        "path": "/0rebc2l8z0wu/6yBVlZPMTwQz9uu40asSIK/3a954d2f79d1b166fe087b8d47003640/guest-content-video-90-29a189a7-d876-4c98-bc4e-5619b04e3c3d-bu5v.jpeg-1707389392904?w=688&h=386&f=center&fit=fill",
                        "width": 688,
                        "height": 386
                    },
                    "largeRetina": {
                        "title": "guest-content-video-90-29a189a7-d876-4c98-bc4e-5619b04e3c3d-bu5v.jpeg",
                        "path": "/0rebc2l8z0wu/6yBVlZPMTwQz9uu40asSIK/3a954d2f79d1b166fe087b8d47003640/guest-content-video-90-29a189a7-d876-4c98-bc4e-5619b04e3c3d-bu5v.jpeg-1707389392904?w=860&h=482&f=center&fit=fill",
                        "width": 860,
                        "height": 482
                    }
                },
                "submissionInfo": "Submission Type: Portal\nUser ID: 90-29a189a7-d876-4c98-bc4e-5619b04e3c3d\nUser Name: MyHayDay",
                "creator": {
                    "7iq6CF8ZXrdL4yb-ucm5s9Ap-No6mCSJGLCVZxaWQNI": {
                        "type": "communityCreator",
                        "name": "MyHayDay",
                        "creatorId": "90-29a189a7-d876-4c98-bc4e-5619b04e3c3d",
                        "submissionInfo": "Submission Type: Portal\nUser ID: 90-29a189a7-d876-4c98-bc4e-5619b04e3c3d\nUser Name: MyHayDay",
                        "thumbnail": {
                            "default": {
                                "height": 640,
                                "width": 640,
                                "title": "Guest content creator 90 29a189a7 d876 4c98 bc4e 5619b04e3c3d xz6h",
                                "path": "/0rebc2l8z0wu/VceQXn8VpTYRecfd8PKHn_AR1W_-rr8J_HNKxQbFBqE/54450c983d8983c4473990ac9c9b2a92/1539741710_1665677633.jpeg"
                            }
                        }
                    }
                },
                "embed": {
                    "url": "https://youtu.be/yDylV6Ww1Cw",
                    "provider": "youtube",
                    "id": ""
                },
                "type": "communityEntry",
                "newUntil": "1707562191"
            },
            {
                "id": "6uXyD1PSdwmdsleiRmYjQT",
                "postDate": "1707117828",
                "expiryDate": null,
                "lang": "en",
                "section": "communityEntries",
                "categories": [],
                "title": "First Time Catching 2 Giant Fishes in Global Fishing Event",
                "videoUrl": "https://youtu.be/0J8yNhCrEr8",
                "author": "GuestContent",
                "embedVideo": false,
                "thumbnail": {
                    "small": {
                        "title": "guest-content-video-90-29a189a7-d876-4c98-bc4e-5619b04e3c3d-srhe.jpeg",
                        "path": "/0rebc2l8z0wu/4RzNcwVBG4DfaX7BIakTt8/f39f929401995e429002c9e8fd831123/guest-content-video-90-29a189a7-d876-4c98-bc4e-5619b04e3c3d-srhe.jpeg-1707117821740?w=172&h=96&f=center&fit=fill",
                        "width": 172,
                        "height": 96
                    },
                    "smallRetina": {
                        "title": "guest-content-video-90-29a189a7-d876-4c98-bc4e-5619b04e3c3d-srhe.jpeg",
                        "path": "/0rebc2l8z0wu/4RzNcwVBG4DfaX7BIakTt8/f39f929401995e429002c9e8fd831123/guest-content-video-90-29a189a7-d876-4c98-bc4e-5619b04e3c3d-srhe.jpeg-1707117821740?w=344&h=193&f=center&fit=fill",
                        "width": 344,
                        "height": 193
                    },
                    "medium": {
                        "title": "guest-content-video-90-29a189a7-d876-4c98-bc4e-5619b04e3c3d-srhe.jpeg",
                        "path": "/0rebc2l8z0wu/4RzNcwVBG4DfaX7BIakTt8/f39f929401995e429002c9e8fd831123/guest-content-video-90-29a189a7-d876-4c98-bc4e-5619b04e3c3d-srhe.jpeg-1707117821740?w=430&h=241&f=center&fit=fill",
                        "width": 430,
                        "height": 241
                    },
                    "mediumRetina": {
                        "title": "guest-content-video-90-29a189a7-d876-4c98-bc4e-5619b04e3c3d-srhe.jpeg",
                        "path": "/0rebc2l8z0wu/4RzNcwVBG4DfaX7BIakTt8/f39f929401995e429002c9e8fd831123/guest-content-video-90-29a189a7-d876-4c98-bc4e-5619b04e3c3d-srhe.jpeg-1707117821740?w=516&h=289&f=center&fit=fill",
                        "width": 516,
                        "height": 289
                    },
                    "large": {
                        "title": "guest-content-video-90-29a189a7-d876-4c98-bc4e-5619b04e3c3d-srhe.jpeg",
                        "path": "/0rebc2l8z0wu/4RzNcwVBG4DfaX7BIakTt8/f39f929401995e429002c9e8fd831123/guest-content-video-90-29a189a7-d876-4c98-bc4e-5619b04e3c3d-srhe.jpeg-1707117821740?w=688&h=386&f=center&fit=fill",
                        "width": 688,
                        "height": 386
                    },
                    "largeRetina": {
                        "title": "guest-content-video-90-29a189a7-d876-4c98-bc4e-5619b04e3c3d-srhe.jpeg",
                        "path": "/0rebc2l8z0wu/4RzNcwVBG4DfaX7BIakTt8/f39f929401995e429002c9e8fd831123/guest-content-video-90-29a189a7-d876-4c98-bc4e-5619b04e3c3d-srhe.jpeg-1707117821740?w=860&h=482&f=center&fit=fill",
                        "width": 860,
                        "height": 482
                    }
                },
                "submissionInfo": "Submission Type: Portal\nUser ID: 90-29a189a7-d876-4c98-bc4e-5619b04e3c3d\nUser Name: MyHayDay",
                "creator": {
                    "7iq6CF8ZXrdL4yb-ucm5s9Ap-No6mCSJGLCVZxaWQNI": {
                        "type": "communityCreator",
                        "name": "MyHayDay",
                        "creatorId": "90-29a189a7-d876-4c98-bc4e-5619b04e3c3d",
                        "submissionInfo": "Submission Type: Portal\nUser ID: 90-29a189a7-d876-4c98-bc4e-5619b04e3c3d\nUser Name: MyHayDay",
                        "thumbnail": {
                            "default": {
                                "height": 640,
                                "width": 640,
                                "title": "Guest content creator 90 29a189a7 d876 4c98 bc4e 5619b04e3c3d xz6h",
                                "path": "/0rebc2l8z0wu/VceQXn8VpTYRecfd8PKHn_AR1W_-rr8J_HNKxQbFBqE/54450c983d8983c4473990ac9c9b2a92/1539741710_1665677633.jpeg"
                            }
                        }
                    }
                },
                "embed": {
                    "url": "https://youtu.be/0J8yNhCrEr8",
                    "provider": "youtube",
                    "id": ""
                },
                "type": "communityEntry",
                "newUntil": "1707290620"
            },
            {
                "id": "16DbCMlBWhLZbLz6wVWi1K",
                "postDate": "1707049775",
                "expiryDate": null,
                "lang": "en",
                "section": "communityEntries",
                "categories": [],
                "title": "New Leaderboards, Hearts Event",
                "videoUrl": "https://youtu.be/zYW9bC9epjg",
                "author": "GuestContent",
                "embedVideo": false,
                "thumbnail": {
                    "small": {
                        "title": "guest-content-video-88-1027c0c1-7b57-4c63-8a92-2c6ce47d910e-z4ib.png",
                        "path": "/0rebc2l8z0wu/66kOpwgKbxCSAy4iUB77qt/f93e815ab8c1522a5ad006359568b584/guest-content-video-88-1027c0c1-7b57-4c63-8a92-2c6ce47d910e-z4ib.png-1707049768564?w=172&h=96&f=center&fit=fill",
                        "width": 172,
                        "height": 96
                    },
                    "smallRetina": {
                        "title": "guest-content-video-88-1027c0c1-7b57-4c63-8a92-2c6ce47d910e-z4ib.png",
                        "path": "/0rebc2l8z0wu/66kOpwgKbxCSAy4iUB77qt/f93e815ab8c1522a5ad006359568b584/guest-content-video-88-1027c0c1-7b57-4c63-8a92-2c6ce47d910e-z4ib.png-1707049768564?w=344&h=193&f=center&fit=fill",
                        "width": 344,
                        "height": 193
                    },
                    "medium": {
                        "title": "guest-content-video-88-1027c0c1-7b57-4c63-8a92-2c6ce47d910e-z4ib.png",
                        "path": "/0rebc2l8z0wu/66kOpwgKbxCSAy4iUB77qt/f93e815ab8c1522a5ad006359568b584/guest-content-video-88-1027c0c1-7b57-4c63-8a92-2c6ce47d910e-z4ib.png-1707049768564?w=430&h=241&f=center&fit=fill",
                        "width": 430,
                        "height": 241
                    },
                    "mediumRetina": {
                        "title": "guest-content-video-88-1027c0c1-7b57-4c63-8a92-2c6ce47d910e-z4ib.png",
                        "path": "/0rebc2l8z0wu/66kOpwgKbxCSAy4iUB77qt/f93e815ab8c1522a5ad006359568b584/guest-content-video-88-1027c0c1-7b57-4c63-8a92-2c6ce47d910e-z4ib.png-1707049768564?w=516&h=289&f=center&fit=fill",
                        "width": 516,
                        "height": 289
                    },
                    "large": {
                        "title": "guest-content-video-88-1027c0c1-7b57-4c63-8a92-2c6ce47d910e-z4ib.png",
                        "path": "/0rebc2l8z0wu/66kOpwgKbxCSAy4iUB77qt/f93e815ab8c1522a5ad006359568b584/guest-content-video-88-1027c0c1-7b57-4c63-8a92-2c6ce47d910e-z4ib.png-1707049768564?w=688&h=386&f=center&fit=fill",
                        "width": 688,
                        "height": 386
                    },
                    "largeRetina": {
                        "title": "guest-content-video-88-1027c0c1-7b57-4c63-8a92-2c6ce47d910e-z4ib.png",
                        "path": "/0rebc2l8z0wu/66kOpwgKbxCSAy4iUB77qt/f93e815ab8c1522a5ad006359568b584/guest-content-video-88-1027c0c1-7b57-4c63-8a92-2c6ce47d910e-z4ib.png-1707049768564?w=860&h=482&f=center&fit=fill",
                        "width": 860,
                        "height": 482
                    }
                },
                "submissionInfo": "Submission Type: Portal\nUser ID: 88-1027c0c1-7b57-4c63-8a92-2c6ce47d910e\nUser Name: R3DKNIGHT",
                "creator": {
                    "ZgedE6WKnqIRZTFt1zeNmsTRfHmliZyKTNPx1xfU2gg": {
                        "type": "communityCreator",
                        "name": "R3DKNIGHT",
                        "creatorId": "88-1027c0c1-7b57-4c63-8a92-2c6ce47d910e",
                        "submissionInfo": "Submission Type: Portal\nUser ID: 88-1027c0c1-7b57-4c63-8a92-2c6ce47d910e\nUser Name: R3DKNIGHT",
                        "thumbnail": {
                            "default": {
                                "height": 50,
                                "width": 50,
                                "title": "Guest content creator 88 1027c0c1 7b57 4c63 8a92 2c6ce47d910e eguh",
                                "path": "/0rebc2l8z0wu/L2j2r7ADuBaQmm1p9m5WCHMhLwDEU4Keap5aJYT9DGg/62f34cceeb563adf084fa29201e0d402/74821364_1656343701.png"
                            }
                        }
                    }
                },
                "embed": {
                    "url": "https://youtu.be/zYW9bC9epjg",
                    "provider": "youtube",
                    "id": ""
                },
                "type": "communityEntry",
                "newUntil": "1707222568"
            }
        ]
    },
    "globals": {
        "globalText.copyToClipboard": "Copy to clipboard!",
        "globalText.langVoteDefaultButtonLabel": "Vote",
        "globalText.thanksForVoting": "Thanks for voting",
        "globalText.langVoteResultsButtonLabel": "Show Results",
        "globalText.close": "Close",
        "globalText.langVoteSubmitLabel": "Submit",
        "globalText.langVoteCheck": "Check vote",
        "globalText.langFollowUs": "Follow Us!",
        "globalText.langNewer": "Newer",
        "globalText.langNew": "New",
        "globalText.langGo": "Go!",
        "globalText.langBy": "By:",
        "globalText.langLoadMore": "Load More",
        "globalText.langOlder": "Older",
        "globalText.langOutOfFeed": "Looks like you\u2019re out of feed.",
        "globalText.langDay": "day",
        "globalText.langDaysAgo": "{x} days ago",
        "globalText.langDays": "days",
        "globalText.langHoursAgo": "{x} hours ago",
        "globalText.langDayAgo": "{x} day ago",
        "globalText.langHourAgo": "{x} hour ago",
        "globalText.langCastYourVote": "Cast Your Vote",
        "globalText.langMinutesAgo": "{x} minutes ago",
        "globalText.langMinutesAbbreviated": "min",
        "globalText.langHoursAbbreviated": "h",
        "globalText.langMinuteAgo": "{x} minute ago",
        "globalText.langHoursCountdown": "Hours",
        "globalText.langYouVoted": "You Voted",
        "globalText.langLoading": "Loading...",
        "globalText.langHourCountdown": "Hour",
        "globalText.langVoteTryAgainLabel": "Vote - Try Again",
        "globalText.langSecondCountdown": "Second",
        "globalText.langSecondsCountdown": "Seconds",
        "globalText.langEndsIn": "Ends In",
        "globalText.langMinuteCountdown": "Minute",
        "globalText.langMinutesCountdown": "Minutes",
        "globalText.langSecondsAbbreviated": "sec"
    }
}